vheader/__init__.py
vheader-0.1.1.dist-info/LICENSE
vheader-0.1.1.dist-info/METADATA
vheader-0.1.1.dist-info/WHEEL
vheader-0.1.1.dist-info/entry_points.txt
vheader-0.1.1.dist-info/top_level.txt
vheader-0.1.1.dist-info/RECORD
