Metadata-Version: 2.1
Name: vheader
Version: 0.1.1
Summary: Generate perfect Vyper code headers every time.
Requires-Python: >=3.8
License-File: LICENSE
Requires-Dist: pyperclip >=1.9.0
